{
  "name" : "IReceiveinfo",
  "originTableName" : "i_receiveinfo",
  "comment" : null,
  "fullColumn" : [ {
    "name" : "id",
    "comment" : null,
    "type" : null,
    "shortType" : null,
    "ktShortType" : "Int",
    "custom" : false,
    "ext" : { }
  }, {
    "name" : "receiveorder",
    "comment" : null,
    "type" : null,
    "shortType" : null,
    "ktShortType" : "Int",
    "custom" : false,
    "ext" : { }
  }, {
    "name" : "name",
    "comment" : null,
    "type" : null,
    "shortType" : null,
    "ktShortType" : "String",
    "custom" : false,
    "ext" : { }
  }, {
    "name" : "tel",
    "comment" : null,
    "type" : null,
    "shortType" : null,
    "ktShortType" : "String",
    "custom" : false,
    "ext" : { }
  }, {
    "name" : "receiveaddress",
    "comment" : null,
    "type" : null,
    "shortType" : null,
    "ktShortType" : "String",
    "custom" : false,
    "ext" : { }
  }, {
    "name" : "receiveunit",
    "comment" : null,
    "type" : null,
    "shortType" : null,
    "ktShortType" : "String",
    "custom" : false,
    "ext" : { }
  }, {
    "name" : "idcard",
    "comment" : null,
    "type" : null,
    "shortType" : null,
    "ktShortType" : "String",
    "custom" : false,
    "ext" : { }
  }, {
    "name" : "memo",
    "comment" : null,
    "type" : null,
    "shortType" : null,
    "ktShortType" : "String",
    "custom" : false,
    "ext" : { }
  }, {
    "name" : "isaddress",
    "comment" : null,
    "type" : null,
    "shortType" : null,
    "ktShortType" : "Int",
    "custom" : false,
    "ext" : { }
  } ],
  "pkColumn" : null,
  "otherColumn" : null,
  "savePackageName" : "com.cuit.wjlocp",
  "savePath" : "./src/main/java/com/cuit/wjlocp",
  "saveModelName" : "wjlocp"
}